sleepyq/__init__.py
sleepyq-0.8.1.dist-info/METADATA
sleepyq-0.8.1.dist-info/WHEEL
sleepyq-0.8.1.dist-info/top_level.txt
sleepyq-0.8.1.dist-info/RECORD
