Metadata-Version: 2.1
Name: sleepyq
Version: 0.8.1
Summary: SleepIQ API for Python
Home-page: http://github.com/technicalpickles/sleepyq
Author: Josh Nichols
Author-email: josh@technicalpickles.com
License: MIT
Platform: UNKNOWN
Requires-Dist: requests
Requires-Dist: inflection
